certitude/__init__.py
certitude/_certitude.py
certitude/api.py
certitude/build.py
certitude/certitude.py
certitude/ertitude.pyd
certitude-1.0.1.dist-info/DESCRIPTION.rst
certitude-1.0.1.dist-info/METADATA
certitude-1.0.1.dist-info/RECORD
certitude-1.0.1.dist-info/WHEEL
certitude-1.0.1.dist-info/metadata.json
certitude-1.0.1.dist-info/top_level.txt
